dds_cli/__init__.py
dds_cli/__main__.py
dds_cli/account_manager.py
dds_cli/auth.py
dds_cli/base.py
dds_cli/constants.py
dds_cli/custom_decorators.py
dds_cli/data_getter.py
dds_cli/data_lister.py
dds_cli/data_putter.py
dds_cli/data_remover.py
dds_cli/directory.py
dds_cli/exceptions.py
dds_cli/file_compressor.py
dds_cli/file_encryptor.py
dds_cli/file_handler.py
dds_cli/file_handler_local.py
dds_cli/file_handler_remote.py
dds_cli/message_helper.py
dds_cli/motd_manager.py
dds_cli/options.py
dds_cli/project_creator.py
dds_cli/project_info.py
dds_cli/project_status.py
dds_cli/s3_connector.py
dds_cli/status.py
dds_cli/superadmin_helper.py
dds_cli/text_handler.py
dds_cli/timestamp.py
dds_cli/unit_manager.py
dds_cli/user.py
dds_cli/utils.py
dds_cli/version.py
dds_cli/dds_gui/__init__.py
dds_cli/dds_gui/app.py
dds_cli/dds_gui/dds_state_manager.py
dds_cli/dds_gui/components/__init__.py
dds_cli/dds_gui/components/dds_button.py
dds_cli/dds_gui/components/dds_container.py
dds_cli/dds_gui/components/dds_footer.py
dds_cli/dds_gui/components/dds_form.py
dds_cli/dds_gui/components/dds_input.py
dds_cli/dds_gui/components/dds_modal.py
dds_cli/dds_gui/components/dds_select.py
dds_cli/dds_gui/components/dds_status_chip.py
dds_cli/dds_gui/components/dds_text_item.py
dds_cli/dds_gui/pages/__init__.py
dds_cli/dds_gui/pages/project_view.py
dds_cli/dds_gui/pages/authentication/__init__.py
dds_cli/dds_gui/pages/authentication/authentication.py
dds_cli/dds_gui/pages/authentication/authentication_form.py
dds_cli/dds_gui/pages/authentication/modals/__init__.py
dds_cli/dds_gui/pages/authentication/modals/login_modal.py
dds_cli/dds_gui/pages/authentication/modals/logout_modal.py
dds_cli/dds_gui/pages/authentication/modals/reauthenticate_modal.py
dds_cli/dds_gui/pages/project_view_mode/__init__.py
dds_cli/dds_gui/pages/project_view_mode/project_actions.py
dds_cli/dds_gui/pages/project_view_mode/project_actions_tabs/__init__.py
dds_cli-2.13.0.dist-info/licenses/LICENSE
dds_cli-2.13.0.dist-info/METADATA
dds_cli-2.13.0.dist-info/WHEEL
dds_cli-2.13.0.dist-info/entry_points.txt
dds_cli-2.13.0.dist-info/top_level.txt
dds_cli-2.13.0.dist-info/RECORD
