Metadata-Version: 2.4
Name: dds_cli
Version: 2.13.0
Summary: A command line tool to manage data and projects in the SciLifeLab Data Delivery System.
Home-page: https://github.com/ScilifelabDataCentre/dds_cli
Author: SciLifeLab Data Centre
License: MIT
Classifier: Development Status :: 4 - Beta
Classifier: License :: OSI Approved :: MIT License
Classifier: Programming Language :: Python :: 3.8
Classifier: Programming Language :: Python :: 3.9
Classifier: Programming Language :: Python :: 3.10
Classifier: Programming Language :: Python :: 3.11
Classifier: Programming Language :: Python :: 3.12
License-File: LICENSE
Requires-Dist: boto3==1.24.73
Requires-Dist: botocore==1.27.73
Requires-Dist: click==8.1.3
Requires-Dist: click-pathlib==2020.3.13.0
Requires-Dist: cryptography==44.0.1
Requires-Dist: immutabledict==2.2.1
Requires-Dist: jwcrypto==1.5.6
Requires-Dist: prettytable==3.7.0
Requires-Dist: prompt-toolkit==3.0.40
Requires-Dist: PyNaCl==1.5.0
Requires-Dist: pytz==2022.2.1
Requires-Dist: PyYAML==6.0.2
Requires-Dist: questionary==1.10.0
Requires-Dist: requests==2.32.4
Requires-Dist: rich==13.6.0
Requires-Dist: rich-click==1.5.2
Requires-Dist: simplejson==3.17.6
Requires-Dist: tzlocal==4.2
Requires-Dist: zstandard==0.23.0
Requires-Dist: textual==2.1.2
Dynamic: author
Dynamic: classifier
Dynamic: description
Dynamic: description-content-type
Dynamic: home-page
Dynamic: license
Dynamic: license-file
Dynamic: requires-dist
Dynamic: summary
